sms_bomb/bomber.py
sms_bomb-1.0.2.dist-info/WHEEL
sms_bomb-1.0.2.dist-info/METADATA
sms_bomb-1.0.2.dist-info/RECORD
