Metadata-Version: 2.1
Name: sms-bomb
Version: 1.0.2
Summary: Простая библиотека для создания ваших смс-бомберов.
Home-page: https://github.com/zalsy/sms-bomb/
Author: zelsy
Requires-Python: >=3.7,<4.0
Classifier: Programming Language :: Python :: 3
Classifier: Programming Language :: Python :: 3.7
Classifier: Programming Language :: Python :: 3.8
Classifier: Programming Language :: Python :: 3.9
Requires-Dist: requests (>=2.24.0,<3.0.0)
